inheritance_explorer/__init__.py
inheritance_explorer/_testing.py
inheritance_explorer/_widget_support.py
inheritance_explorer/cli.py
inheritance_explorer/inheritance_explorer.py
inheritance_explorer/similarity.py
inheritance_explorer/tests/__init__.py
inheritance_explorer/tests/test_cli.py
inheritance_explorer/tests/test_inheritance_explorer.py
inheritance_explorer/tests/test_similarity.py
inheritance_explorer/tests/test_utilities.py
inheritance_explorer/tests/test_widgets.py
inheritance_explorer-0.2.0.dist-info/AUTHORS.rst
inheritance_explorer-0.2.0.dist-info/LICENSE
inheritance_explorer-0.2.0.dist-info/METADATA
inheritance_explorer-0.2.0.dist-info/WHEEL
inheritance_explorer-0.2.0.dist-info/entry_points.txt
inheritance_explorer-0.2.0.dist-info/top_level.txt
inheritance_explorer-0.2.0.dist-info/RECORD
