Metadata-Version: 2.1
Name: inheritance_explorer
Version: 0.2.0
Summary: A tool for exploring complex inheritance patters in python code
Author-email: Chris Havlin <chris.havlin@gmail.com>
License: MIT License
Project-URL: Homepage, https://github.com/data-exp-lab/inheritance_explorer
Project-URL: Bug Tracker, https://github.com/data-exp-lab/inheritance_explorer/issues
Classifier: Development Status :: 4 - Beta
Classifier: Intended Audience :: Developers
Classifier: License :: OSI Approved :: MIT License
Classifier: Natural Language :: English
Classifier: Programming Language :: Python :: 3
Classifier: Programming Language :: Python :: 3.8
Classifier: Programming Language :: Python :: 3.9
Classifier: Programming Language :: Python :: 3.10
Requires-Python: >=3.8
License-File: LICENSE
License-File: AUTHORS.rst
Requires-Dist: pydot
Requires-Dist: pycode-similar
Requires-Dist: numpy
Requires-Dist: matplotlib
Requires-Dist: pyvis
Requires-Dist: networkx
Requires-Dist: click
Requires-Dist: ipywidgets
Requires-Dist: jupyterlab
Provides-Extra: dev
Requires-Dist: pytest >=3 ; extra == 'dev'
Requires-Dist: pytest-cov ; extra == 'dev'
Requires-Dist: yt >4.1 ; extra == 'dev'
Requires-Dist: pre-commit ; extra == 'dev'
Provides-Extra: docs
Requires-Dist: Sphinx ==7.3.7 ; extra == 'docs'
Requires-Dist: jinja2 ==3.1.4 ; extra == 'docs'
Requires-Dist: nbsphinx ; extra == 'docs'
Provides-Extra: lint
Requires-Dist: black ==22.8.0 ; extra == 'lint'
Requires-Dist: isort ==5.12.0 ; extra == 'lint'
Requires-Dist: flake8 ==6.0.0 ; extra == 'lint'
